{
  "batch_number": 2,
  "candidate_count": 50,
  "candidates": [
    {
      "id": 51,
      "handle": "heartofkailua",
      "display_name": "Julianne King",
      "bio": "Community\nLet's change the understanding of autism! Mother, wife, friend.....taking action is my antidote. Www... \nmore\nhawaiiautismfoundation.org\nFollow\nMessage\n10.28",
      "profile_url": "https://www.instagram.com/heartofkailua/",
      "follower_count": 3767,
      "following_count": 2213,
      "post_count": 627,
      "is_business": false,
      "is_verified": false,
      "website": "hawaiiautismfoundation.org",
      "website_content": "0 \n \n \n \n \n \n\n \n\n \n \n \n \n \n\n \n \n \n\n \n \n \n\n \n \n \n\n \n \n \n \n \n \n \n \n \n \n \n \n \n \n \n \n \n \n \n \n \n \n \n \n \n \n \n \n \n \n \n \n \n \n \n\n \n \n \n \n\n \n \n \n \n\n \n \n \n \n \n \n \n\n \n \n \n\n \n \n \n Skip to Content\n \n \n\n \n \n \n \n \n\n \n \n \n\n \n \n\n \n\n \n\n \n\n \n\n \n \n \n \n \n \n \n \n \n \n\n \n\n \n \n \n \n \n \n \n \n \n \n\n \n \n\n \n \n \n \n \n \n \n \n \n \n \n\n \n \n \n Our Programs\n \n \n \n \n \n\n \n \n \n \n Events\n \n \n \n \n \n \n \n \n Social Events\n \n \n \n \n \n \n \n \n \n \n Upcoming Events\n \n \n \n \n \n \n \n \n \n \n\n \n \n \n \n Spelling to Communicate\n \n \n \n \n \n \n \n \n About S2C\n \n \n \n \n \n \n \n \n \n \n S2C Resources\n \n \n \n \n \n \n \n \n \n \n Practioners\n \n \n \n \n \n \n \n \n \n \n\n \n \n \n \n Local Resources\n \n \n \n \n \n \n \n \n Local Resources\n \n \n \n \n \n \n \n \n \n \n CIT Officers and Autism\n \n \n \n \n \n \n \n \n \n \n\n \n \n \n About Us\n \n \n \n \n \n\n \n \n \n Donate\n \n \n \n \n \n\n \n \n \n \n \n \n \n \n \n \n \n \n \n \n\n \n\n \n \n\n \n \n \n \n\n \n \n \n \n\n \n \n \n \n\n \n\n \n \n \n Open Menu \n Close Menu \n \n \n \n \n \n \n \n \n \n\n \n \n \n \n \n\n \n \n \n \n \n \n \n \n \n \n \n\n \n\n \n \n \n \n \n \n \n \n \n \n\n \n \n\n \n \n \n \n \n \n \n \n \n \n \n\n \n \n \n Our Programs\n \n \n \n \n \n\n \n \n \n \n Events\n \n \n \n \n \n \n \n \n Social Events\n \n \n \n \n \n \n \n \n \n \n Upcoming Events\n \n \n \n \n \n \n \n \n \n \n\n \n \n \n \n Spelling to Communicate\n \n \n \n \n \n \n \n \n About S2C\n \n \n \n \n \n \n \n \n \n \n S2C Resources\n \n \n \n \n \n \n \n \n \n \n Practioners\n \n \n \n \n \n \n \n \n \n \n\n \n \n \n \n Local Resources\n \n \n \n \n \n \n \n \n Local Resources\n \n \n \n \n \n \n \n \n \n \n CIT Officers and Autism\n \n \n \n \n \n \n \n \n \n \n\n \n \n \n About Us\n \n \n \n \n \n\n \n \n \n Donate\n \n \n \n \n \n\n \n \n \n \n \n \n \n \n \n \n \n \n \n \n\n \n\n \n \n\n \n \n \n \n\n \n \n \n \n\n \n \n \n \n\n \n\n \n \n \n Open Menu"
    },
    {
      "id": 352,
      "handle": "kukoludesigns",
      "display_name": "KU\u0304 KOLU DESIGNS",
      "bio": "Local business\nWholesale: kukoludesigns@gmail.com\nlinktr.ee/kukoludesigns\nFollow\nMessage\nCUSTOMER PHOTOS\nNECKLACES\nEARRINGS\nMEDIA\nEVENTS\nSTOCKISTS\nBRACELETS\nCUSTOM\nOHANA SETS\nMAMA & KEIKI",
      "profile_url": "https://www.instagram.com/kukoludesigns/",
      "follower_count": 3753,
      "following_count": 4176,
      "post_count": 742,
      "is_business": false,
      "is_verified": false,
      "website": "gmail.com",
      "website_content": "Sign in to continue to Gmail Email or phone Forgot email? Not your computer? Use a private browsing window to sign in. Learn more about using Guest mode Next Create account Afrikaans az\u0259rbaycan bosanski catal\u00e0 \u010ce\u0161tina Cymraeg Dansk Deutsch eesti English (United Kingdom) English (United States) Espa\u00f1ol (Espa\u00f1a) Espa\u00f1ol (Latinoam\u00e9rica) euskara Filipino Fran\u00e7ais (Canada) Fran\u00e7ais (France) Gaeilge galego Hrvatski Indonesia isiZulu \u00edslenska Italiano Kiswahili latvie\u0161u lietuvi\u0173 magyar Melayu Nederlands norsk o\u2018zbek polski Portugu\u00eas (Brasil) Portugu\u00eas (Portugal) rom\u00e2n\u0103 shqip Sloven\u010dina sloven\u0161\u010dina srpski (latinica) Suomi Svenska Ti\u1ebfng Vi\u1ec7t T\u00fcrk\u00e7e \u0395\u03bb\u03bb\u03b7\u03bd\u03b9\u03ba\u03ac \u0431\u0435\u043b\u0430\u0440\u0443\u0441\u043a\u0430\u044f \u0431\u044a\u043b\u0433\u0430\u0440\u0441\u043a\u0438 \u043a\u044b\u0440\u0433\u044b\u0437\u0447\u0430 \u049b\u0430\u0437\u0430\u049b \u0442\u0456\u043b\u0456 \u043c\u0430\u043a\u0435\u0434\u043e\u043d\u0441\u043a\u0438 \u043c\u043e\u043d\u0433\u043e\u043b \u0420\u0443\u0441\u0441\u043a\u0438\u0439 \u0441\u0440\u043f\u0441\u043a\u0438 (\u045b\u0438\u0440\u0438\u043b\u0438\u0446\u0430) \u0423\u043a\u0440\u0430\u0457\u043d\u0441\u044c\u043a\u0430 \u10e5\u10d0\u10e0\u10d7\u10e3\u10da\u10d8 \u0570\u0561\u0575\u0565\u0580\u0565\u0576 \u202b\u05e2\u05d1\u05e8\u05d9\u05ea\u202c\u200e \u202b\u0627\u0631\u062f\u0648\u202c\u200e \u202b\u0627\u0644\u0639\u0631\u0628\u064a\u0629\u202c\u200e \u202b\u0641\u0627\u0631\u0633\u06cc\u202c\u200e \u12a0\u121b\u122d\u129b \u0928\u0947\u092a\u093e\u0932\u0940 \u092e\u0930\u093e\u0920\u0940 \u0939\u093f\u0928\u094d\u0926\u0940 \u0985\u09b8\u09ae\u09c0\u09af\u09bc\u09be \u09ac\u09be\u0982\u09b2\u09be \u0a2a\u0a70\u0a1c\u0a3e\u0a2c\u0a40 \u0a97\u0ac1\u0a9c\u0ab0\u0abe\u0aa4\u0ac0 \u0b13\u0b21\u0b3c\u0b3f\u0b06 \u0ba4\u0bae\u0bbf\u0bb4\u0bcd \u0c24\u0c46\u0c32\u0c41\u0c17\u0c41 \u0c95\u0ca8\u0ccd\u0ca8\u0ca1 \u0d2e\u0d32\u0d2f\u0d3e\u0d33\u0d02 \u0dc3\u0dd2\u0d82\u0dc4\u0dbd \u0e44\u0e17\u0e22 \u0ea5\u0eb2\u0ea7 \u1019\u103c\u1014\u103a\u1019\u102c \u1781\u17d2\u1798\u17c2\u179a \ud55c\uad6d\uc5b4 \u4e2d\u6587\uff08\u9999\u6e2f\uff09 \u65e5\u672c\u8a9e \u7b80\u4f53\u4e2d\u6587 \u7e41\u9ad4\u4e2d\u6587 Help Privacy Terms"
    },
    {
      "id": 462,
      "handle": "cookieclips",
      "display_name": "\u26a0\ufe0fWARNING TOO CUTE\u26a0\ufe0f",
      "bio": "\ud83d\udc36Cookie\ud83d\udebaShihtzu \ud83c\udf3aHI.Oahu \ud83c\udf897.31.10\n\ud83c\udfa52nd account for all my silly videos & edits!\n\ud83d\udcf8IG photos @cookie_luv_club\nlinktr.ee/cookie_luv_club\nFollow\nMain Account",
      "profile_url": "https://www.instagram.com/cookieclips/",
      "follower_count": 3696,
      "following_count": 1536,
      "post_count": 826,
      "is_business": false,
      "is_verified": false,
      "website": "linktr.ee/cookie_luv_club",
      "website_content": "@cookie_luv_club Alohapawsco Code:ALOHACOOKIE10 Alohapawsco Code:ALOHACOOKIE10 Azpetwearhi Code:COOKIE15 Azpetwearhi Code:COOKIE15 Poochlook Code:COOKIE15 Poochlook Code:COOKIE15 Chicpuppy Code:COOKIELUV Chicpuppy Code:COOKIELUV PuppyloveHi bandanas PuppyloveHi bandanas Walgreens Photo Deals Walgreens Photo Deals Find photo coupon codes, discounts, promo codes and all the latest deals at Walgreens Photo center. Save on Christmas cards, invitations, and much more. Soulpals St.pats Pawty 3/17 Soulpals St.pats Pawty 3/17 Moanalua Off-leash Dog Park Moanalua Off-leash Dog Park HHS - Paws on the Path hiking club HHS - Paws on the Path hiking club Video IG @cookieclips Video IG @cookieclips Sky Waikiki - free beach towel Sky Waikiki - free beach towel Hawaii Pet Beat - Hub info events Hawaii Pet Beat - Hub info events Island Dog Magazine- Photo submission Island Dog Magazine- Photo submission Cookie Surgery Gofund Cookie Surgery Gofund Cookie Preferences \u2022 Report \u2022 Privacy \u2022 Explore Explore other Linktrees @theageofeera @theunapologeticceo @kidheights @vds.london @youthvgov @djdannysmith @mink_hotsw33t @jarritos_benelux @drkoh.ca @andrewfinney @hair_by_carley_ @jfeventsandflowers @capacityforcommunity @thecareermomco @rxforliberty @melbournebeachflooringkitchens @dahtwintowers @hausofmix @thehillishome @ireadispell @gelato.love @yasmine.yamada @growwithidea.com @dullboycustoms @tntgrazersgalore @geronimoandsonsplumbing @katiejobagley @chloegirlsworld @LOYALTOREGGAE @backtobeverly @specklepark"
    },
    {
      "id": 305,
      "handle": "melissasnc6",
      "display_name": "Melissa Sanchez",
      "bio": "Toulouse \ud83d\udccd\ud83d\udccd\nMia \ud83d\udc36\nfreya \ud83d\udc08\u200d\u2b1b\nmelissasnc6\nFollow\nnanimoooooo\n\u2764\ufe0f\n\ud83d\udcaa\ud83d\udcaa\ud83d\udcaa\ud83d\udcaa\nles copaing\ud83c\udf7b\ud83e\udd42",
      "profile_url": "https://www.instagram.com/melissasnc6/",
      "follower_count": 3544,
      "following_count": 6244,
      "post_count": 130,
      "is_business": false,
      "is_verified": false,
      "website": ""
    },
    {
      "id": 102,
      "handle": "finnowitz",
      "display_name": "Amanda Finn",
      "bio": "\ud83d\udccdHawai'i / casting + flying\nFollow",
      "profile_url": "https://www.instagram.com/finnowitz/",
      "follower_count": 3481,
      "following_count": 1548,
      "post_count": 490,
      "is_business": false,
      "is_verified": false,
      "website": ""
    },
    {
      "id": 48,
      "handle": "galaxychihuahuas",
      "display_name": "\ud83d\udcabGalaxy Chihuahua\u2019s",
      "bio": "Digital creator\n\ud83d\udcabOahu,Hawaii! \ud83c\udf3a\ud83c\udfdd\ufe0f\ud83c\udf0aWe are passionate and dedicated in raising well socialized, top quality applehead Chihuahuas to AKC... \nmore\nsites.google.com/view/galaxychihuahuas/home and 5 more\ngalaxychihuahuas\nFollow\nMessage\nHighlights\nGalaxychihuahua\nHighlights",
      "profile_url": "https://www.instagram.com/galaxychihuahuas/",
      "follower_count": 3478,
      "following_count": 2303,
      "post_count": 802,
      "is_business": false,
      "is_verified": false,
      "website": "sites.google.com/view/galaxychihuahuas/home",
      "website_content": "Search this site Embedded Files Skip to main content Skip to navigation Galaxy Chihuahuas Home Available Puppies Meet the Parents Past Puppies Contact Us Galaxy Chihuahuas Home Available Puppies Meet the Parents Past Puppies Contact Us More Home Available Puppies Meet the Parents Past Puppies Contact Us Welcome to Galaxy Chihuahuas! \ud83c\udf34We are located in Hawaii\ud83c\udf34 You can find us on Facebook, TikTok, and Instagram: Galaxy Chihuahua's WELCOME!\u00a0 We have recently moved to Hawaii on the beautiful island of Oahu.\u00a0 \ud83c\udfdd\ufe0f\ud83c\udf0a All of our puppies are raised in our home and very well socialized with people and other animals. We are a hobby breeder who cares about the overall quality of\u00a0 the applehead chihuahuas and strives to breed within the AKC standard. Our goal is to raise healthy, happy, puppies with friendly temperaments. All parents are on site. Each puppy will have a full vet exam, deworming, and proper vaccinations before leaving for their new home. \u00a0Our puppies are sold as \"pet only\" with no papers or breeding rights.\u00a0 We look forward to helping yo u find the perfect addition to your family!! FAQs Frequently asked questions: Where are you located? Makakilo, Hawaii (Oahu) How much are your puppies? Prices start at $5000 and go up.\u00a0 Price depends on the individual puppy. Do you ship? No, but we can meet you at a local airport for a small fee depending on travel time. Do you have a waiting list? No. We prefer you fill out our puppy application to see if you are a good fit for one of our puppies."
    },
    {
      "id": 252,
      "handle": "getchokelove",
      "display_name": "Choke Love \ud83c\udf4d",
      "bio": "Once upon a time there lived a beautiful surfer who wanted to fill the world with Choke (meaning alot) Love and making... \nmore\nwww.etsy.com/shop/ChokeLove\nFollow",
      "profile_url": "https://www.instagram.com/getchokelove/",
      "follower_count": 3334,
      "following_count": 3445,
      "post_count": 74,
      "is_business": false,
      "is_verified": false,
      "website": "www.etsy.com/shop/ChokeLove"
    },
    {
      "id": 39,
      "handle": "fizzgigs_mom",
      "display_name": "Stacie's Leis and Charms",
      "bio": "DM or text me at 808-285-5259 for orders\n#stacieslistofleis\n*Craft fairs* 2/14, Japanese Cultural Center of Hawaii... \nmore\ndocs.google.com/presentation/d/10iInJzpu-8F4JsaWDln5iMcEcyunj7kOJoeqED9tsrc/edit\nFollow\nMessage\nPrices\nLei Maintenance\nLei Collection\nOur Babies\nHow to order\nResin\nFur Friends 2\nFur Friends 3\nFur Friends\nLei Po'o\nPeople Leis\nContact\nPet Leis",
      "profile_url": "https://www.instagram.com/fizzgigs_mom/",
      "follower_count": 3186,
      "following_count": 2766,
      "post_count": 1598,
      "is_business": true,
      "is_verified": false,
      "website": "docs.google.com/presentation/d/10iInJzpu-8F4JsaWDln5iMcEcyunj7kOJoeqED9tsrc/edit",
      "website_content": "This browser version is no longer supported. Please upgrade to a supported browser. Stacie\u2019s Lei and Charms Tab \u00a0 \u00a0 External \u00a0 \u00a0 \u00a0 \u00a0 \u00a0 \u00a0 \u00a0 Slideshow \u00a0 \u00a0 Share Sign in File Edit View Help Accessibility Debug \u00a0 \u00a0 Unsaved changes to Drive \u00a0 \u00a0 \u00a0 \u00a0 \u00a0 \u00a0 \u00a0 \u00a0 Accessibility \u00a0 \u00a0 View only \u00a0 \u00a0 \u00a0 \u00a0 \u00a0 HTML view of the presentation"
    },
    {
      "id": 108,
      "handle": "northshoresurfgirls",
      "display_name": "North Shore Surf Girls",
      "bio": "Product/service\nLocally owned surf school on Oahu's fabled North Shore. | Book a lesson with us today online\\! \ud83c\udf0a\ud83c\udfc4\u200d\u2640\ufe0f\ud83c\udfc4@northshoresurfgirls\nKahalewai Place, Haleiwa, Hawaii 96712\nwww.northshoresurfgirls.com\nnorthshoresurfgirls\nFollow\nMessage\nHappy Vale Day\\!\nMele Kalikimaka\nSurf Lessons\nNorth Shore Life\nHighlights\nMiss Poli\nHighlights\nOriginal Team\\!\nstay home\nHighlights\nLife is good\\!\nHighlights\nHighlights\nHighlights",
      "profile_url": "https://www.instagram.com/northshoresurfgirls/",
      "follower_count": 3143,
      "following_count": 1919,
      "post_count": 1275,
      "is_business": true,
      "is_verified": false,
      "website": "www.northshoresurfgirls.com",
      "website_content": "Skip to content \n \n Home Book Lessons Group Surf Lessons Family Private Surf Lesson Private & Semi-Private Surf Lessons Tandem Special Surf Lesson Exclusive Large Group Surf Lessons Turtle Tour and Surf Lesson Sunset BBQ & Surf Lesson Stand up Paddle Board Rental River Turtle Tour and Stand up Paddle Board Lesson Gift Cards Surf Lesson Locations Chun\u2019s Beach Puaena Point About us Our Story Merchandise Gallery Blog FAQs Contact us \n Home Book Lessons Group Surf Lessons Family Private Surf Lesson Private & Semi-Private Surf Lessons Tandem Special Surf Lesson Exclusive Large Group Surf Lessons Turtle Tour and Surf Lesson Sunset BBQ & Surf Lesson Stand up Paddle Board Rental River Turtle Tour and Stand up Paddle Board Lesson Gift Cards Surf Lesson Locations Chun\u2019s Beach Puaena Point About us Our Story Merchandise Gallery Blog FAQs Contact us \n \n \n \n \n 808-637-2977 \n \n \n \n \n \n \n Surf Lessons on the Legendary North Shore Safe, fun, and unforgettable surf lessons for men, women, and families. Join us in the water! \n \n \n Book Surf \n \n \n \n \n Learn More \n \n Learn to Surf on the North Shore - Small Groups, Local Instructors Beginner-friendly surf lessons for men, women, and kids. Local & family-owned. No experience needed, with flexible scheduling. Group Surf Lessons \n $65.95 - $89.95 \n Book 1 & 1.5 hr lesson \n \n \n View Details \n \n Private & Semi-Private Surf Lessons \n $119.95 - $225.95 \n Book a Lesson \n \n \n View Details \n \n Tandem Special Surf Lesson \n $159.95 \n Book a Lesson \n \n \n View"
    },
    {
      "id": 4,
      "handle": "caninecardiohawaii",
      "display_name": "Mobile Dog Gym",
      "bio": "\ud83d\udccdOahu\nClimate controlled\u2744\ufe0f\ud83e\udd76\nONLY mobile dog gym in Hawaii! \ud83d\ude90\ud83d\udc15\nOwned and operated by a veterinary professional \ud83e\ude7a\ud83d\udc3e\nDM to... \nmore\nwww.caninecardiohawaii.com and 2 more\nFollow\nMessage\nFAQs\nService Areas\nMerch!\nPricing\nBackstory",
      "profile_url": "https://www.instagram.com/caninecardiohawaii/",
      "follower_count": 3070,
      "following_count": 925,
      "post_count": 120,
      "is_business": false,
      "is_verified": false,
      "website": "www.caninecardiohawaii.com",
      "website_content": "top of page Client Login \n \n \n \n \n Menu \n \n \n \n \n \n \n Close \r\n \n \n \n \n \n Home About Contact FAQ Pricing Canine Cardio Hawaii \n Where Health Meets Happiness Unleash your dog's energy! Get Started Introduction Canine Cardio Hawaii LLC is Hawaii's first and only veterinary professional owned mobile dog gym! We are a Kailua based, female owned and operated, dog-powered exercise service that provides an easy and safe alternative way to exercise your dog. I come to your home and provide a fulfilling and safe workout for your dog in my fully equipped and climate controlled trailer. I am here to help the dogs of Hawai'i live a happier, healthier, and longer life through regular exercise. Canine Cardio Hawaii is where health meets happiness! What is a mobile dog gym? \r\n \n \n \n \n \n \n \n \n \n \n \n \n \n \n Temperature Controlled Our trailer is equipped with cold air conditioning to ensure that your dog can exercise comfortably, no matter the weather conditions outside. \r\n \n \n \n \n \n \n \n \n \n \n \n \n \n \n 100% Pup-Powered Our treadmills (called slatmills) are specifically designed with dogs in mind. They are low resistance, low impact, and have no motor, so your dog can go as fast (or slow) as they want and even stop if they are tired. Safety is ensured by clipping the dogs harness to the slatmill so that they don't fall off and dogs are continuously monitored by our expert coach. \r\n \n \n \n \n \n Convenient We come to you! This makes exercising your dog easier than ever. As long as there is a parking space"
    },
    {
      "id": 88,
      "handle": "alohaajsheltie",
      "display_name": "AJ, Bi-black Sheltie in Hawaii",
      "bio": "Bi-black Sheltie causing mischief in Hawaii. \ud83c\udfdd\ufe0f\ud83c\udf3aAgility and treat enthusiast!\nLet's be pup friends \ud83d\udc3e\n#AlohaAJSheltie\nFollow\nMessage",
      "profile_url": "https://www.instagram.com/alohaajsheltie/",
      "follower_count": 3015,
      "following_count": 2922,
      "post_count": 94,
      "is_business": false,
      "is_verified": false,
      "website": ""
    },
    {
      "id": 180,
      "handle": "ricksellssd",
      "display_name": "Rick Ramirez",
      "bio": "San Diego Realtor | Metro San Diego Specialist | Financial Services\nCA DRE#02108754\nCompass\nlinktr.ee/ricksellssd\nFollow\nMessage\nSan Diego\nHaw\u00e1i\nNYC\nAmsterdam\nParis",
      "profile_url": "https://www.instagram.com/ricksellssd/",
      "follower_count": 2902,
      "following_count": 4829,
      "post_count": 194,
      "is_business": false,
      "is_verified": false,
      "website": "linktr.ee/ricksellssd",
      "website_content": "@ricksellssd California native with a passion for building wealth through real estate. CA DRE #02108754 eXp Realty of S. CA. Inc. #0218730 Search for Homes Search for Homes LinkedIn LinkedIn Zillow Reviews Zillow Reviews Facebook Facebook Instagram Instagram Cookie Preferences \u2022 Report \u2022 Privacy \u2022 Explore Explore other Linktrees @GeorgiaMcGrath @CabinetPragma2626 @wearepallas.io @Jmeeksapothecary @danni.duncan_ @LuisAponte @phil.the.flavours @magnusalexander @eleni.ispoglou @besttalkintown @deliveruk @layla.reseller @gnaiauthority @billyreekie @gavyndiviney @rraybaee @brightstarcare.mcdonough @personalisedphotogifts @ConnorGoodrich.Finance.Broker @Clover.Ellena.Andreolli @npuc_y @bonesandbuilds @xmtech @lishalayedit @chiahowteoh @thepotluckclubldn @wavlyhealth @edgefitnessclubs @chrisediger @katieandcourage @BDEP @bellahall @sophden @Reconnectlegacy @iamdjdmoney @TimKessler @PrimeSupp_Shop @tekapo @luis_medrano_experimental @prod.tom @favodoces @photographyasprayer @LunFitHub @hunnywoodz @deivid.bitti View on mobile"
    },
    {
      "id": 342,
      "handle": "kaleboy711",
      "display_name": "Nicolas Kale Los Ba\u00f1os",
      "bio": "\u271d\ufe0f Exodus 14:14\n\ud83c\udf0bHawai\u02bbi \ud83c\udf3a\ud83e\udd19\ud83c\udffc #aloha\n\u270f\ufe0f Artwork: @alakuma_art\n\ud83d\udc9c #endALZ: @alzhawaii",
      "profile_url": "https://www.instagram.com/kaleboy711/",
      "follower_count": 2878,
      "following_count": 4096,
      "post_count": 4440,
      "is_business": false,
      "is_verified": false,
      "website": ""
    },
    {
      "id": 69,
      "handle": "brotherdogs_kk",
      "display_name": "Kenai, Koda, Nalu, Mikey, & Carina",
      "bio": "\ud83d\udccdOahu\nKenai- White Shepherd\nKoda- Yellow Lab\nNalu- White Swiss Shepherd\n... \nmore\nwww.nonstopdogwear.com/BROTHERS\nbrotherdogs_kk\nFollow\nMessage\nNalu x Jet\nThings for sale\nKapa x Koda\nLily x Nalu\nMada x Nalu\nNALUS FAVE\nKENAI'S FAVE\nKODAS FAVE\nK9tactical gear\nRants",
      "profile_url": "https://www.instagram.com/brotherdogs_kk/",
      "follower_count": 2751,
      "following_count": 2628,
      "post_count": 1014,
      "is_business": false,
      "is_verified": false,
      "website": "www.nonstopdogwear.com/BROTHERS",
      "website_content": "Skip to content\n \n\n \n \n\n \n \n\n \n\n \n \n \n \n \n \n Your cart is empty \n \n \n \n \n \n Continue shopping\n Have an account? \n \n Log in to check out faster.\n \n \n Your cart \n \n \n \n \n \n\n \n \n \n\n \n\n \n \n\n \n \n \n \n \n Loading...\n \n \n \n \n \n \n \n \n \n\n \n You May Also Like \n\n \n \n \n \n \n Line harness 5.0 \n 699,00 kr \n\n \n \n Quick View\n\n \n \n\n \n \n \n \n \n \n \n \n \n \n \n \n \n \n \n \n Fjord raincoat \n 959,00 kr \n\n \n \n Quick View\n\n \n \n\n \n \n \n \n \n \n \n \n \n \n \n \n \n \n \n \n Bungee leash \n 649,00 kr \n\n \n \n Quick View\n\n \n \n\n \n \n \n \n \n \n \n \n \n \n \n \n \n \n \n \n Freemotion harness 5.0 \n 1.199,00 kr \n\n \n \n Quick View\n\n \n \n\n \n \n \n \n \n \n \n \n \n \n \n \n \n \n \n \n Protector bootie \n 379,00 kr \n\n \n \n Quick View\n\n \n \n\n \n \n \n \n \n \n \n \n \n \n \n \n \n \n \n \n Long distance bootie \n 149,00 kr \n\n \n \n Quick View\n\n \n \n\n \n \n \n \n \n \n \n \n \n \n \n \n \n \n \n\n \n\n \n \n \n \n\n \n \n\n \n Estimated total \n 0,00 NOK \n \n\n Taxes included. Discounts and shipping calculated at checkout.\n \n \n\n \n\n \n \n Check out\n \n \n\n \n \n \n\n \n \n \n \n \n \n \n \n \n \n \n \n \n \n \n \n \n \n \n \n \n\n \n \n \n \n \n \n \n 2 Year Warranty \n \n\n \n \n \n \n \n 2-5 Business Days \n \n\n \n \n \n \n \n 60 Day Free Returns \n \n \n\n \n\n \n \n \n \n \n \n\n \n \n \n \n\n \n\n \n \n \n \n \n \n \n \n \n \n \n 60 days free returns \n \n \n \n \n \n \n \n Country/region \n\n \n \n Norway |\n NOK\n kr \n \n\n \n \n \n \n \n \n Search \n \n \n \n \n \n \n \n \n \n \n \n \n \n \n \n \n Afghanistan \n \n USD\n $ \n \n \n \n \n \n \u00c5land Islands \n \n USD\n $ \n \n \n \n \n \n Albania \n \n USD\n $ \n \n \n \n \n \n Algeria \n \n USD\n $ \n \n \n \n \n \n Andorra \n \n USD\n $ \n \n \n \n \n \n Angola \n \n USD\n $ \n \n \n \n \n \n Anguilla \n \n USD\n $ \n \n \n \n \n \n Antigua &"
    },
    {
      "id": 697,
      "handle": "the_spud_life",
      "display_name": "Hawaiian George & Fred (SDiT)",
      "bio": "A L \ud83c\udf3a H A, we are George and Fred, da cutest potatoes (French Bulldogs) living it up in Hawaii. (SDiT\ud83d\udea8) Follow us on...\u00a0\nmore\nFollow",
      "profile_url": "https://www.instagram.com/the_spud_life/",
      "follower_count": 2705,
      "following_count": 6799,
      "post_count": 230,
      "is_business": false,
      "is_verified": false,
      "website": ""
    },
    {
      "id": 31,
      "handle": "its_ben_awhile1",
      "display_name": "Ben Bryce",
      "bio": "Art Consultant \ud83d\uddbc\nReal Estate Investor \ud83c\udfe0 Puppy Raiser \ud83d\udc36\nLanc\u2014>Nash\u2014>SD\u2014>Oahu\ud83d\udccd\nwww.benjaminrbryce.com\nFollow\nMessage\nSummit\nBoomer\nMolly\nSky\nArt\nWesson\nMikey\nClifton\nGeorge\nGus\nSkydiving",
      "profile_url": "https://www.instagram.com/its_ben_awhile1/",
      "follower_count": 2694,
      "following_count": 1605,
      "post_count": 75,
      "is_business": false,
      "is_verified": false,
      "website": "www.benjaminrbryce.com",
      "website_content": "Benjamin R Bryce Benjamin R Bryce Benjamin R Bryce Benjamin R Bryce Benjamin R Bryce Benjamin R Bryce Benjamin R Bryce Benjamin R Bryce Home About Contact More Home About Contact Home About Contact Naval Officer Writer Art Consultant - Benjamin Bryce Naval Officer Writer Art Consultant - Benjamin Bryce Naval Officer Writer Art Consultant - Benjamin Bryce Naval Officer Writer Art Consultant - Benjamin Bryce He is a Naval Officer, an accomplished writer, and an experienced Art Consultant. Contact Me Publications An unlikely friendship: How an undergrad formed a forever bond with a cancer patient at Vanderbilt The Randy Lowe story is an inspiring tale of a dedicated Naval Officer who transitioned into a successful Art Consultant, leveraging his unique experiences and insights. His journey has been featured in various publications, showcasing the intersection of his military background and artistic pursuits. Read Here Vanderbilt University students want growing concern over mold taken seriously The Fight for Clean Air has drawn attention from various professionals, including an Art Consultant who emphasizes the importance of visual awareness in environmental issues, and a Naval Officer who advocates for cleaner air policies based on their experience at sea. Together, they contribute to important Publications that highlight the ongoing struggle for a healthier atmosphere. Read Here USA Today: \"Sexual assault is a huge threat to women in US military. We have a duty to do better.\" Sexual"
    },
    {
      "id": 436,
      "handle": "whoozagoodog",
      "display_name": "Whooza Goodog (WAGD Hawaii)",
      "bio": "\ud83d\udc36 Dog Goods & Services \ud83d\udc3e\n\ud83c\udf3aKALAHEO, KAUAI\ud83c\udf3a\n@mahinawithdogs\nwww.wagdhawaii.com\nFollow\nMessage\n\ud83d\udc15\ud83d\udc15",
      "profile_url": "https://www.instagram.com/whoozagoodog/",
      "follower_count": 2689,
      "following_count": 2392,
      "post_count": 498,
      "is_business": false,
      "is_verified": false,
      "website": "www.wagdhawaii.com"
    },
    {
      "id": 428,
      "handle": "auwsyl",
      "display_name": "AUW Society of Young Leaders",
      "bio": "Nonprofit organization\nAloha United Way Society of Young Leaders is a group of young professionals who make a positive impact in Hawai\u02bbi!...\u00a0\nmore\nlinktr.ee/auwsyl\nFollow\nMessage\n2025 FTK\nSERVE\n2024 FTK",
      "profile_url": "https://www.instagram.com/auwsyl/",
      "follower_count": 2672,
      "following_count": 1686,
      "post_count": 724,
      "is_business": false,
      "is_verified": false,
      "website": "linktr.ee/auwsyl",
      "website_content": "@auwsyl Aloha United Way Society of Young Leaders [VOLUNTEER] Ma\u02bbi Movement Kit Making Day - Feb 21, 2026 [VOLUNTEER] Ma\u02bbi Movement Kit Making Day - Feb 21, 2026 Eventbrite - Aloha United Way Society of Young Leaders presents Ma\u02bbi Movement Kit Making Day - Saturday, February 21, 2026 in Honolulu, HI. Find event and ticket information. >> BECOME A MEMBER << >> BECOME A MEMBER << New Member Info Request Form New Member Info Request Form Board & Committee Interest Form Board & Committee Interest Form Mahalo for your interest in serving on an SYL Committee or the Board! Please fill out this form to start and one of our board members will follow up with you. About Society of Young Leaders About Society of Young Leaders The Aloha United Way Society of Young Leaders strives to engage the next generation of leaders in making Hawai\u2018i a better place. Together, we give, serve and learn to make a collective, positive impact on the most pressing issues in our community. Cookie Preferences \u2022 Report \u2022 Privacy \u2022 Explore Explore other Linktrees @lauren.luber @texashaulstars @lyanna_ @hattabesthost @goodtrip.co.uk @roomster @doitride @OakleySI @belhelcom @mkworkshop @LamaraSpa @nicparkhillhair @nicolewild @agi.brevardflrealtor @luizagonzalez @thelonecanary @kiransweetkaur14 @cellarmastersla @bunacafeamazing @classcars @opkoutletpremium @barbagrossaoficial @Stu45 @DigitalBusinessServices @PuttsForePints @Wangari.Co @sayoofficial @AIBlock @ivan.fitfactor @jessicadallasrealestate @precisionplay_1"
    },
    {
      "id": 152,
      "handle": "hawaiianeye797",
      "display_name": "Craig Fujii",
      "bio": "Hawaii is home, and it's a joy and privilege to photograph her sealife - a quarter of which are unique to the islands... \nmore\nFollow",
      "profile_url": "https://www.instagram.com/hawaiianeye797/",
      "follower_count": 2662,
      "following_count": 3112,
      "post_count": 3925,
      "is_business": false,
      "is_verified": false,
      "website": ""
    },
    {
      "id": 96,
      "handle": "icandogs",
      "display_name": "ICAN",
      "bio": "We unleash possibility by facilitating partnerships between people and dogs.\n5100 Charles Ct, Suite 100, Zionsville, Indiana 46077\nICAN and 4 more\nFollow\nMessage\nWine&Wags 2022",
      "profile_url": "https://www.instagram.com/icandogs/",
      "follower_count": 2618,
      "following_count": 756,
      "post_count": 1248,
      "is_business": false,
      "is_verified": false,
      "website": ""
    },
    {
      "id": 105,
      "handle": "purplepupgo",
      "display_name": "Pet Transport | Flight Nanny | Dallas, TX",
      "bio": "Pet Service\nWe travel the world with your pets. \ud83d\udc36\ud83d\udc08\u200d\u2b1b\ud83d\udc30\nFlight Nanny \u2708\ufe0f\u2708\ufe0f\u2708\ufe0f\nPrivate Ground Transport \ud83d\ude97\ud83d\ude97\ud83d\ude97\nMessage me for a custom trans... \nmore\n76051\nwww.purplepup.net and 2 more\npurplepupgo\nFollow\nMessage\nLondon\nSpain\nIndia\nFrance\nShop Faves\nDog Jets\nAmsterdam\nCopenhagen\nBrazil\nItaly\nThailand\nHawaii\n\u274cstandby\u274c\nAdvice",
      "profile_url": "https://www.instagram.com/purplepupgo/",
      "follower_count": 2567,
      "following_count": 1790,
      "post_count": 381,
      "is_business": false,
      "is_verified": false,
      "website": "www.purplepup.net",
      "website_content": "top of page Home Flights Domestic Flights International Flights Travel Nanny Shared Pet Jets Puppies Cats Ground Shared Routes Quote Reviews F.A.Q Shop Resources More Use tab to navigate through the menu items. PurplePup LLC \n \n \n \n \n Pet Transportation Services \n Accompanied pet travel solutions \n \n \n \n \n Are you moving or welcoming a new furry family member? PurplePup provides personalized luxury pet transportation services, including ground transport and flight nanny services, to ensure your dog, cat, or rabbit arrives home with the utmost care and comfort. Our USDA Registered and Insured company is dedicated to delivering exceptional service and communication, making your experience as joyful and stress-free as possible. Reach out for a customized quote tailored to your family's needs. \n\n \u00a0 \n\n Watch this video to explore our premium services! >>> \n\n \u00a0 \n\n -Amanda, Owner, PurplePup LLC Pet Transportation Services Have your small fur baby hand delivered to you by our flight nannies. We fly confirmed commercial flights with your pets inside the cabin of the plane.\u00a0 Flight Nanny for Pets Request a Flight Nanny \n \n \n \n \n Large dogs, pets with special needs, or families with multiple pets can travel comfortably by ground in an air-conditioned vehicle. We provide GPS tracking and daily photo updates.\u00a0 Ground Transportation for Dogs Request a Ride \n \n \n \n \n Our Values PETS FIRST \n Every decision we make considers the comfort, health, and safety of your pet above all else \n \n LEAD WITH"
    },
    {
      "id": 163,
      "handle": "waikikicommunitycenter",
      "display_name": "Waikiki Community Center",
      "bio": "Community\nWaikiki hub for Community, Connection & Care \ud83c\udf08 Events, Workshops & Activities. Support for Keiki to Kupuna \ud83c\udf34 Preschool &... \nmore\n310 Paoakalani Ave, Honolulu, Hawaii 96815\nWaikiki Community Center and 1 more\nFollow\nMessage\nNew Mural\nWaikiki Lights",
      "profile_url": "https://www.instagram.com/waikikicommunitycenter/",
      "follower_count": 2557,
      "following_count": 1672,
      "post_count": 650,
      "is_business": false,
      "is_verified": false,
      "website": ""
    },
    {
      "id": 171,
      "handle": "wocuniteorg",
      "display_name": "WOCunite",
      "bio": "Community\nBe a Beacon of Hope \ud83d\udcab\nwocunite.org/donate and 2 more\nwocuniteorg\nFollow\nMessage",
      "profile_url": "https://www.instagram.com/wocuniteorg/",
      "follower_count": 2483,
      "following_count": 504,
      "post_count": 413,
      "is_business": false,
      "is_verified": false,
      "website": "wocunite.org/donate",
      "website_content": "Skip to content \n \n \n \n \n \n \n \n About \n Press & Media Kit \n Podcast \n Our Team \n Events \n Consultancy \n Fiscal Sponsorship \n Non-Profit Production \n #Startwith8 Program \n Hire From The JTC List \n Take Action \n \n WOCU Seal \n Screenwriting Contest Transparency \n Reimagine Casting \n \n \n Shop \n \n\n \n\n \n \n \n \n \n \n \n \n\n \n \n \n \u00d7 \n \n \n About \n Press & Media Kit \n Podcast \n Our Team \n Events \n Consultancy \n Fiscal Sponsorship \n Non-Profit Production \n #Startwith8 Program \n Hire From The JTC List \n Take Action \n \n WOCU Seal \n Screenwriting Contest Transparency \n Reimagine Casting \n \n \n Shop \n \n \n \n \n \n \n \n \n \n Instagram \n \n \n \n \n Threads \n \n \n \n \n Tiktok \n \n \n \n \n Facebook-f \n \n \n \n \n \n \n \n \n \n \n \n \n \n \n \n \n \n \n \n \n \n \n \n \n \n \n \n \n \n \n \n \n \n \n \n DONATE \n \n \n \n \n \n \n \n \n \n \n \n \n \n \n \n \n \n \n \n \n \n \n \n \n DONATE TO WOCU \n \n \n \n \n \n \n \n \n \n \n \n \n \n \n \n \n Your donations are used to promote fair hiring, fair access and fair treatment for Women of Color working in the entertainment industry. Women of Color-run non-profits only receive 0.5% of all grant/foundation money because of systemic racism and sexism. ( source ) The funds available for women-focused non-profits is systematically granted to white female led groups, and rarely makes its way to Women of Color. ( source ) This is why it is vital to donate to Women of Color Unite directly. We accept donations via Every.Org \u2013 please click the button below to donate. \n \n \n \n \n \n \n \n \n \n \n \n \n \n \n \n \n \n \n \n \n \n \n \n Donate"
    },
    {
      "id": 288,
      "handle": "hondawindwardhi",
      "display_name": "Honda Windward",
      "bio": "",
      "profile_url": "https://www.instagram.com/hondawindwardhi/",
      "follower_count": 2483,
      "following_count": 6038,
      "post_count": 2232,
      "is_business": false,
      "is_verified": false,
      "website": "iconwww.hondawindward.com/index.htm"
    },
    {
      "id": 58,
      "handle": "tailshawaii",
      "display_name": "Tails of Hawaii | Hawaii\u2019s Best Pet Boarding and Daycare",
      "bio": "Pet Service\ud83d\udc36 Doggie Daycare\ud83d\udc3e Dog & Cat Boarding\ud83d\udec1 Spa Services\u2708\ufe0f Pet Transport @tailmovershawaii\u2615\ufe0f Sit & Sip Cafe98-751 Kuahao Pl, St 102, Pearl City, Hawaii 96782",
      "profile_url": "https://www.instagram.com/tailshawaii/",
      "follower_count": 2466,
      "following_count": 298,
      "post_count": 1595,
      "is_business": false,
      "is_verified": false,
      "website": "iconwww.tailsofhawaii.com"
    },
    {
      "id": 372,
      "handle": "konatoa",
      "display_name": "Kona",
      "bio": "Public figure\nAloha! This is Kona \ud83d\udc3e\n\ud83d\udccd Honolulu, HI\n\ud83c\udf82 3/5/2018\n\ud83d\udc9dAdopted 3/26/2020\n\ud83e\uddecEmbark Ambassador\nFollow\nMessage\nModel Codes\nSupDog\nBarkHaus",
      "profile_url": "https://www.instagram.com/konatoa/",
      "follower_count": 2439,
      "following_count": 3763,
      "post_count": 430,
      "is_business": false,
      "is_verified": false,
      "website": ""
    },
    {
      "id": 165,
      "handle": "macy_da_opihi",
      "display_name": "Macy | Dog Tricks \u2022 Hawaii",
      "bio": "Macy \ud83d\udc3e & DeAnna \ud83d\udc69\ud83c\udffb | Dog Trick Creator\nAussie Goldendoodle \u2022 Hawaii \ud83c\udf3a\nConfidence > perfection\nTeaching play-based dog... \nmore\nlinktr.ee/macy_da_opihi and 1 more\nFollow\nMessage\nMeet Macy\nBalance\nHold\nJumps",
      "profile_url": "https://www.instagram.com/macy_da_opihi/",
      "follower_count": 2374,
      "following_count": 2633,
      "post_count": 320,
      "is_business": false,
      "is_verified": false,
      "website": "linktr.ee/macy_da_opihi",
      "website_content": "Macy A mini Aussie golden doodle who loves to shop, do tricks and be goofy! Instagram Instagram Macy and Mom's Amazon Page Macy and Mom's Amazon Page Shop recommended products from Macy and Mom on www.amazon.com. Learn more about Macy and Mom's favorite products. YouTube: Macy_da_opihi YouTube: Macy_da_opihi The Honest Kitchen Human Grade Pet Food (MACY_DA_OPIHI for 40% off firs purchase) The Honest Kitchen Human Grade Pet Food (MACY_DA_OPIHI for 40% off firs purchase) Pupford (code MACYDAOPIHI for 10% off) Pupford (code MACYDAOPIHI for 10% off) Pupford Pink Papyrus (code MACY for 10% off) Pink Papyrus (code MACY for 10% off) Cookie Preferences \u2022 Report \u2022 Privacy \u2022 Explore Explore other Linktrees @zuwi68yt @_lifewithcharl @homewithbriana @doterrabgeu @rosslawgroup @DizzyDays @jodiekstrom_ifbbpro @Front2back @olgaplishko @bonitartistry @dearyouhealth @Home4UPteLtd @ElAposentoAlto @drshellyharrell @bringinginspirationhome @etuisyen @tobhk @rechsteinerrentalmgmt @paulk_music @utilitysolutionsinc @DieShowMitChris @viernesdeimpacto @brickandmortarnwa @junkjournals_scrapbookmemories @joliecafe @chaads @stayhea @refletsdemoi @dcmuzicgrp @siphumlemvandaba @emehtyahu @shiticoolers @314grayfox @ScholarFriends @angelaireland @rowhouseua @charlottetilburynottingham @unitedrentalslife @Anzlo @hwgreenroompodcast @JTAre @joseaugusto.imoveis @ceo_boss23 @enlightened.channels @Masseriawave View on mobile"
    },
    {
      "id": 432,
      "handle": "frank_pacheco_main_11123",
      "display_name": "frank_pacheco_main_11123",
      "bio": "Follow",
      "profile_url": "https://www.instagram.com/frank_pacheco_main_11123/",
      "follower_count": 2345,
      "following_count": 2593,
      "post_count": 0,
      "is_business": false,
      "is_verified": false,
      "website": ""
    },
    {
      "id": 200,
      "handle": "hawaiipetportraits",
      "display_name": "HAWAII\u2019S PET PHOTOGRAPHER",
      "bio": "Lifestyle | Commercial | Editorial\nVOTED HONOLULU MAGAZINE'S \"BEST PET & YOU PHOTOS\" JUNE 2020\nAlso at... \nmore\n521 Ala Moana Blvd, M-423, Honolulu, Hawaii 96813\nwww.hawaiipetportraits.com/winter-wonderland-pet-mini-sessions-1\nFollow\nMessage",
      "profile_url": "https://www.instagram.com/hawaiipetportraits/",
      "follower_count": 2341,
      "following_count": 972,
      "post_count": 219,
      "is_business": false,
      "is_verified": false,
      "website": "www.hawaiipetportraits.com/winter-wonderland-pet-mini-sessions-1"
    },
    {
      "id": 120,
      "handle": "oahudogtraining",
      "display_name": "O\u2019ahu Dog Training | Kristen Davis, Ph.D.",
      "bio": "O'ahu's Original Concierge Dog Trainer - Redefining what's possible when balanced training meets real life.\nwww.oahudogtraining.com\noahudogtraining\nFollow\nMessage\nProgress\nPrograms\nReviews\nAbout Me\nMylo",
      "profile_url": "https://www.instagram.com/oahudogtraining/",
      "follower_count": 2311,
      "following_count": 909,
      "post_count": 570,
      "is_business": false,
      "is_verified": false,
      "website": "www.oahudogtraining.com",
      "website_content": "\b\u0000\u0000\u0000\u0000\u0000\u0004\u0003\u0019\u007fs|=gn\u0014g\f\u0012gl+wi.qZ'3\u0005\u0016X\u000bX%'\u0017{\u000b\u0212\fwvNbk\u001fn^pqy\u0019 (|\u0002\u007f\u0013\u0012?=b\u0011\u0000\u0018u_XF\u0013P( H\n4OA~\u03c0IA\"H\u0016\u001e%F1s`@2(\u0232$\u001dx\u007f\u04ccf8\":\u0001HS!#\u001ax\u0015 g^q! Qo|j\u001b?c\u001a;\u02a8(Q\u0003\u001d\u0122VEq\u075dF\u00102gCk\u0343\u0000Pg\u00173cfl(\u0002jj\u0002JE\u0000bb\u0000j4\u0018\u0386;\\+\u0015P\u07599m|[\u0002\u02b2gmh\u0003%*!\u01e45g\u000b4pk\u0002\u000f.\u0012\u0016k)D\u0013\u0000/aM`0\u0011f)B\u07ae_\u0014N\n[(9\u007fU\u000b\u0005PT$\u01a7\u07e9\u0007\u063a*V\nJmC\u0363G\u001d\b\u0014\u026b]Q$\u001ewPR\u0012Ae9G}\n\u0010T\u000eVt!RmjU\u0001\r!ZS(`N(b\ue800i,i\u0019JbY#>T\u0010.\u0003_B@+-4!\u0006?S`3\u0343\nR\u001a\f^+Z\u0015\u0007I\u0356y\n: \f!1HSD.\u0684,u\"\u01d4\u03c0\"\u001f*\u2cf1veY*a\u02218z\u001e2[n\u0001\u0014M1\u0017Z FU\u0001 W\nPH\u000fj^pM^s\u0001yLfTK8\\Ee\u0001!W\u0005DQtE\u0013F-4\u0017KY\u0000\u0013\u0011J\u07b1\u0005-\"o\u0018z\u0770\u00126GI\f{\u000e\u0649\u0013uRdl\u0015\u00121`o[&CH5/{\u000bIhO2y\u0019 < \u0005LD\nUcE < :10y&&6t!_ E\u0010 w\uf18d!kEW>r,~n:\u0002+v~?%9\u0003\u03fb?E@%\"H\u0542\u0004\bK\u0018]0s\u06ddO*{G88w+^v8\f\u000bRs9\fN\u0001Q\u001e\u0153 < \u0378\u04a0\rc\u0007N&'0\u0006uy\u001c0\u0273\u00124\u0019\u0002\u001fXN\u022eigLB8Q#U( \n\u0003]\u001a`Bj\u0007#Keh=O\u001a\u0000\u001a\u0014\u001f\u000eN\nw\u0002\\J\u001f?Uv\u001eZP\u00136#\u000f\u001e4}\"9\u000fi&E\u05e2]z`-5\u06c6Q3\u054b\u735a\u0001Guq.\\c@\u0080\u000bzV\u0010\u0001X\u0003\u0633y1K[\u05736@wJ,\r{vK\u001fHSM3\u000b\u000e\u000f\u001e}jm`4\u0012tQf\u064cQFT\u001e7a;\"\u03d2 < +Z\u02bfqy\u0527~[C4k\u001bg;\u021e5\u001f\u0012\u0018p(S\fxm.)=|\u0014(cZ\u00b9mz\u001fYC8p\bg#\u000ew!\u000e9)[\u001dk0UV\u000e\u031b5j8o\u0000\u0000\u0000ZMO\u001b1\u0010W \u0003(@h8A\u0010\u0004\rP \u001a\u0001 !%\r;>\u000f\u03fb\u0019Y\u07c6W\u0004*/_\u001aS\u0003$Zs\u0372Ku\u001f=\u001eSG\u0583\u01f6W- \u0007}St\u0543\u02b9\u03ab\u076f\u03f7M{\u0016&K\\\u001eGf!I\u0012R\b\u00187.7\u001fNW6i\u001d(\u001dZynT]\u001fG\u00176GgK \u066d|0ZQI\u0010M6\u007fc\u05d7w,OS\u0012,5\u0007\u001cu,NI%\u000eB\u001b\u0015\n ^D,\u0012 \u02e5[L\r&E3\u04ack[f{w^\u001f-A9J\u0015Zp\u007f1XZ?)\n9Q{ < :Y\u001d?\u0439:X\u001e]iSB\u0018\\?Zm\u06eeFnq;uw\u000b \"\u0016\u0004\u0011\u001c_{[\u0004h!v\u0004\u00033%{_L>^,H\fi 9$IOsiw\u000eGc \u001c5|\u0011Et,o\bH/#?J)?t\u0007-\u0003C\u000eX\\=!a\u000f^!a\u000fNH\u0603\u0013\u0012=0\u0011\u0005\u0744\u0007'>\u0019{\bHN5\u001aFS\r#\u0329\u0011T\u00c0#\"\u007ff\u0017hf!zJ=>\u001d'\u0017\u000bTE:\u0004E!9'Og\u0006rs\u0192\u001a7Nk\u05b2\u001f#|\u0172~V]; m\u0010@j\u0019xJb*\u0003\u0007h]=\u001e3)\u0016\u0005/^sr\u00027I9aCA9P:\u0015&j1Cu\u0010\u0019\u0006O\u0015\ba/`\u000b\u0011\u0002\u0001 \u0002\u0005\\\u04d3\u001e@_s8\u0357\u0016z'\u0013}1\u007f\u000fiC\u0003\u000e:oEgSo5:\u779f^\u000e[\ue87fz^`(\u001eoYb \u0016~=^ze#j!;u?J`\u0011$`\\\u0747A)a$J\u009bIT%(Q\u04cc]&\f^fQ\u02cb'7{=l\u0017XN\u0018*1qr->\u0019\";9`XsP\u0004Y|\u0011*{Jt\u00050MEYJ8\u0016\u0012,C#-\u0011O\u02e26\u0012\u0019\u0016\u0760z\u0011n7-\u0010c2N\u05deD+zGv_nA0 63\u0004\u0014yHYH\u000b?RS\u001e\u0007'h\u0133(\rw\\!nY\u0017&1\u007fz\u0470y6\"\\sCD\u0004,nA=7_a\u001c\f~\u0003j3y)\u0018@\u001b6Qq\u0004r&\u001fBUnM\u001a\u032bWa\ued85\u07b4.\u0001nt9-\u0019qhtFJ\\Ny=/~67t}E5\b%\u00153 @Z\u0328l/\bQ3r\u0012\u0003\fF@:[^]: \u051b\u001d\u0014\u001d\u0013\u0685\u0003lPc/~\r\u06aa\u001d;\u0011p/\u000em{~?\u00138}\u000bUZ\u0003.\u00078}M'\u06efNbDb(S;}`/?\u007f15 \u0586u>P:ZY\u0006)9?\u000b+1\u001f\u0015\rWP^pF\u001cL=uNu@\u001a(dWzp\u00acsl\u0012^WD]\u001bn6AU"
    },
    {
      "id": 500,
      "handle": "lolapupttorney",
      "display_name": "lolapupttorney",
      "bio": "Pupttorney at Paw\u2696\ufe0fFloofstorian\ud83d\udcdaNYC\ud83d\uddfdSpecialize in Unlawful Search and Seizure of Treats *Honorary member of...\u00a0\nmore\nwww.gofundme.com/f/vet-bills-for-6-seniors\nFollow\nHolidays 2022\nSummer walks\nPaw Porn",
      "profile_url": "https://www.instagram.com/lolapupttorney/",
      "follower_count": 2188,
      "following_count": 2324,
      "post_count": 960,
      "is_business": false,
      "is_verified": false,
      "website": "www.gofundme.com/f/vet-bills-for-6-seniors",
      "website_content": "Skip to content Search Donate Discover fundraisers and nonprofits to support Categories Browse fundraisers by category Crisis relief Donate to verified relief Social Impact Funds Direct support for urgent needs Supporter Space Inspiration, FAQs, and where to give Nonprofits Give to tax-deductible organizations Fundraise Start fundraising, tips, and resources How to start a GoFundMe Step-by-step help, examples, and more Fundraising categories Find the right category for you Team fundraising Fundraise together with a team Fundraising Blog Resources, tips, and more Fundraising tips The ultimate fundraising tips guide Fundraising ideas Ideas to spark your creativity Charity fundraising Fundraise for a charity Sign up as a nonprofit Claim your nonprofit About How it works, pricing, and more How GoFundMe works GoFundMe Giving Guarantee Supported countries Pricing Help Center About GoFundMe Newsroom Careers GoFundMe.org GoFundMe Partnerships Sign in Start a GoFundMe 0% complete $9,992 raised of \u00a0 10K 148 donations Share Donate now \u200c \u200c \u200c \u200c \u200c \u200c \u200c \u200c \u200c \u200c \u200c \u200c \u200c \u200c \u200c See all See top H Hollie Willingham Vet bills for 6 seniors A K M 148 donors Read story 0% complete $9,992 raised of \u00a0 10K \u200c Share Donate Vet bills for 6 seniors H Hollie Willingham H Hollie Willingham is organizing this fundraiser. Donation protected Hi friends! I have really been struggling lately with the care of my pups. I\u2019ve tried to do everything on my own and really resisted asking for help. I\u2019ve had a few friends encourage"
    },
    {
      "id": 403,
      "handle": "simoneyoneoka",
      "display_name": "Simone Yoneoka",
      "bio": "Health/beauty\nHealth & Wholeness \ud83d\udc9e\nwww.neumi.com/kingdomhealth\nFollow\nMessage\nHighlights\nHighlights\nHighlights\nHighlights\nPSALM 23\nHighlights\nHighlights\nH\u00f6jdpunkter",
      "profile_url": "https://www.instagram.com/simoneyoneoka/",
      "follower_count": 2138,
      "following_count": 3607,
      "post_count": 2015,
      "is_business": false,
      "is_verified": false,
      "website": "www.neumi.com/kingdomhealth",
      "website_content": "United States\r\n \r\n \r\n \r\n \r\n \r\n United States\r\n \r\n \r\n \r\n \r\n \r\n Mexico\r\n \r\n \r\n \r\n \r\n \r\n Australia\r\n \r\n \r\n \r\n \r\n \r\n Austria\r\n \r\n \r\n \r\n \r\n \r\n Belgium\r\n \r\n \r\n \r\n \r\n \r\n Bulgaria\r\n \r\n \r\n \r\n \r\n \r\n Canada\r\n \r\n \r\n \r\n \r\n \r\n Canary Islands\r\n \r\n \r\n \r\n \r\n \r\n Colombia\r\n \r\n \r\n \r\n \r\n \r\n Costa Rica\r\n \r\n \r\n \r\n \r\n \r\n Croatia\r\n \r\n \r\n \r\n \r\n \r\n Cyprus\r\n \r\n \r\n \r\n \r\n \r\n Czech Republic\r\n \r\n \r\n \r\n \r\n \r\n Denmark\r\n \r\n \r\n \r\n \r\n \r\n Dominican Republic\r\n \r\n \r\n \r\n \r\n \r\n Ecuador\r\n \r\n \r\n \r\n \r\n \r\n El Salvador\r\n \r\n \r\n \r\n \r\n \r\n Estonia\r\n \r\n \r\n \r\n \r\n \r\n Finland\r\n \r\n \r\n \r\n \r\n \r\n France\r\n \r\n \r\n \r\n \r\n \r\n Germany\r\n \r\n \r\n \r\n \r\n \r\n Ghana\r\n \r\n \r\n \r\n \r\n \r\n Greece\r\n \r\n \r\n \r\n \r\n \r\n Guadeloupe (French)\r\n \r\n \r\n \r\n \r\n \r\n Guatemala\r\n \r\n \r\n \r\n \r\n \r\n Honduras\r\n \r\n \r\n \r\n \r\n \r\n Hong Kong\r\n \r\n \r\n \r\n \r\n \r\n Hungary\r\n \r\n \r\n \r\n \r\n \r\n Indonesia\r\n \r\n \r\n \r\n \r\n \r\n Ireland\r\n \r\n \r\n \r\n \r\n \r\n Israel\r\n \r\n \r\n \r\n \r\n \r\n Italy\r\n \r\n \r\n \r\n \r\n \r\n Japan NFR\r\n \r\n \r\n \r\n \r\n \r\n Kazakhstan\r\n \r\n \r\n \r\n \r\n \r\n Kenya\r\n \r\n \r\n \r\n \r\n \r\n Latvia\r\n \r\n \r\n \r\n \r\n \r\n Lithuania\r\n \r\n \r\n \r\n \r\n \r\n Luxembourg\r\n \r\n \r\n \r\n \r\n \r\n Malaysia\r\n \r\n \r\n \r\n \r\n \r\n Malta\r\n \r\n \r\n \r\n \r\n \r\n Martinique (French)\r\n \r\n \r\n \r\n \r\n \r\n Morocco\r\n \r\n \r\n \r\n \r\n \r\n Netherlands\r\n \r\n \r\n \r\n \r\n \r\n New Zealand\r\n \r\n \r\n \r\n \r\n \r\n Nigeria\r\n \r\n \r\n \r\n \r\n \r\n Panama\r\n \r\n \r\n \r\n \r\n \r\n Peru\r\n \r\n \r\n \r\n \r\n \r\n Philippines\r\n \r\n \r\n \r\n \r\n \r\n Poland\r\n \r\n \r\n \r\n \r\n \r\n Portugal\r\n \r\n \r\n \r\n \r\n \r\n Qatar\r\n \r\n \r\n \r\n \r\n \r\n Reunion (French)\r\n \r\n \r\n \r\n \r\n \r\n Romania\r\n \r\n \r\n \r\n \r\n \r\n Saint-Martin (French)\r\n \r\n \r\n \r\n \r\n \r\n Saudi Arabia"
    },
    {
      "id": 81,
      "handle": "i.am.keoki",
      "display_name": "Keoki",
      "bio": "Personal blog\ni.am.keoki\nFollow\nMessage\nstuff\nSlut\nBeach\nNatural\nLeather\nLensa\nHalloween\nFolsom 2022",
      "profile_url": "https://www.instagram.com/i.am.keoki/",
      "follower_count": 2134,
      "following_count": 2989,
      "post_count": 227,
      "is_business": false,
      "is_verified": false,
      "website": ""
    },
    {
      "id": 138,
      "handle": "keelikolanimiddle",
      "display_name": "Ke\u2019elik\u014dlani Middle School",
      "bio": "We, the Ke'elik\u014dlani Middle School Ohana, are dedicated to nurturing, inspiring, and empowering all students to be... \nmore\nkeelikolanimiddle.org\nFollow\nMessage\nHI Now\nHighlights\nALS Ice Bucket\nAttendance Arcad\nGTKY\nYMC\nMural Painting\nRelate Break\nFundraising\nYWC\nSY20-21 Updates\nDistance Lng\n#centralpride",
      "profile_url": "https://www.instagram.com/keelikolanimiddle/",
      "follower_count": 2124,
      "following_count": 2461,
      "post_count": 704,
      "is_business": false,
      "is_verified": false,
      "website": "keelikolanimiddle.org",
      "website_content": "top of page Ke\u2018elik\u014dlani Middle School Princess Ruth ABOUT US Principal's Message Mission + Vision School History Health & Safety Hawaii Keiki Corner Academic Plan Accreditation Fall 2021 Dashboard Non-Discrimination Statement Privacy Rights MS4 Guidelines Bulletin Board Renaissance Program School Community Council Video Gallery Photo Gallery Administration and Faculty ACADEMICS Grade 6 Curriculum SY 2025-26 Grade 7 Curriculum SY 2025-26 Grade 8 Curriculum SY 2025-26 Grade 6 Curriculum SY 2026-27 Grade 7 Curriculum SY 2026-27 Grade 8 Curriculum SY 2026-27 Library SBA/HSA Parent Book ANNOUNCEMENTS PARENTS SBA Parent Letter Infinite Campus Breakfast & Lunch Pricing Attendance Policy Tardy Policy Uniform Policy Phone Policy Forms Bell Schedule School Community Council Ohana Help Desk STUDENTS Bulldog Store Backpack Raffle Infinite Campus Clubs & Activities Bell Schedule Breakfast/Lunch Menu Student Calendar Supply List Alma Mater STAFF My Apps Teacher Links Staff Videos Google Translate Custodian Request Form DONATE CONTACT US More Use tab to navigate through the menu items. \u2018Onipa\u2018a We, the Princess Ruth Ke\u2018elik\u014dlani Middle School Ohana, are dedicated to nurture, inspire, and empower all students to be resilient learners. Infinite Campus Breakfast/Lunch Menu Student Calendar UPCOMING EVENTS 09 \nFEB Teacher Institute Day \nNo School 16 \nFEB Presidents' Day \nNo School Student Calendar IN THE NEWS HI Now Daily: Attendance Arcade Watch Video \n\n View Photos Hawaii News Now: Ice Bucket"
    },
    {
      "id": 335,
      "handle": "ohanadoggiedaycare",
      "display_name": "ohanadoggiedaycare",
      "bio": "We are Hawaii'''s first cage-free daycare boarding facility and grooming spa, with over 21 years of experience and happy... \nmore\nwww.ohanadoggiedaycare.net\nFollow",
      "profile_url": "https://www.instagram.com/ohanadoggiedaycare/",
      "follower_count": 2118,
      "following_count": 6753,
      "post_count": 2536,
      "is_business": false,
      "is_verified": false,
      "website": "www.ohanadoggiedaycare.net",
      "website_content": "Close \n\n \n Doggie Cams \n Day Care \n Boarding \n Spa \n Testimonials \n About Us \n FAQ \n \n \n \n Search for: \n \n \n \n \n \n \n \n \n \n \n \n \n Ohana Doggie Daycare \n \n \n \n\n \n \n Doggie Cams \n Day Care \n Boarding \n Spa \n Testimonials \n About Us \n FAQ \n \n \n \n \n \n \n \n \n\n \n \n \n \n \n \n \n \n \n \n \n \n \n \n \n Ohana Doggie Day Care is the first and largest dog daycare in Honolulu, Hawaii proudly serving our community for 20 YEARS! Ohana Doggie Daycare\u2019s mission is to expand the human-dog bond by providing a safe, fun, and stimulating environment for all dogs of all sizes. Come play, socialize, stay, and\u00a0 be pampered. Cage free day care Cage free overnight boarding Doggie spa and grooming \u00a0 Call us for an evaluation at: (808) 791-DOGS (3647) \n \n \n \n \n \n \n \n \n \n \n \n \n \n \n \n \n \n \n \n \n \n \n \n \n \n \n \n \n \n \n \n \n \n \n \n \n \n \n \n We are conveniently located in Kaka\u2019ako at: 611 Cooke Street Honolulu, Hawaii 96813 \u00a0 All dogs must have a socialization evaluation to ensure that this is the right mix for your dog. All dogs must have current DHLLP and current Bordetella within 6 months. We ask for a copy of shot records at your evaluation. Call and schedule yours today. \u00a0 Click here to read our Rules and Regulations. \n \n \n \n \n \n \n \n \n \n \n \n \n \n \n \n \n \n \n \n \n \n \n \n \n \n \n \n \n \n \n \n \n \n \n \n Instagram \n \n \n \n \n Facebook \n \n \n \n \n Youtube \n \n \n \n \n \n \n \n \n \n \n \n \n \n \n \n \n \n \n\n \n Back to top \n \n\n \n\n \n \n \n \n \n \n \n Our Day Care is Open: Monday-Friday 7:00 am-6:30 pm \nSaturday: 8:00-5:00 pm \nSunday: Closed \n Rules and Regulations"
    },
    {
      "id": 55,
      "handle": "izzi_808",
      "display_name": "Izzi Chan",
      "bio": "Real Estate AgentIzzi Chan is Where Aloha Meets Home.Former: Design+Construction+Marketing ==> Current: Realtor Associate at Five... more",
      "profile_url": "https://www.instagram.com/izzi_808/",
      "follower_count": 2029,
      "following_count": 875,
      "post_count": 374,
      "is_business": false,
      "is_verified": true,
      "website": "iconlinktr.ee/izzichan"
    },
    {
      "id": 405,
      "handle": "malhbottsart",
      "display_name": "Mal H Botts",
      "bio": "Artist\nSober Mom. Makes Art. Holds Breath. Bakes Cakes. Writes Books. Avoids Laundry. Occasionally Funny. Homeschool Wannabe...\u00a0\nmore\n34788\nmalhbotts.com/shop-1 and 3 more\nmalhbottsart\nFollow\nMessage",
      "profile_url": "https://www.instagram.com/malhbottsart/",
      "follower_count": 2001,
      "following_count": 2281,
      "post_count": 313,
      "is_business": false,
      "is_verified": false,
      "website": "malhbotts.com/shop-1"
    },
    {
      "id": 117,
      "handle": "mshanapaa.mrkoli",
      "display_name": "Hana\u2764\ufe0fKoli",
      "bio": "Digital creator\nHana adopted from Kona, HI 10/28/20 \ud83c\udfc6 CGC\nKoli @kauaihumanesociety 10/23/23\nBustah \u2764\ufe0f Bendah \ud83d\ude07\ud83d\udc36\ud83c\udf08\n\ud83d\udccdOahu, HI\nMomager... \nmore\nlinktr.ee/MsHanapaa.MrKoli\nFollow\nMessage\nKoli\nMom\nHana\nBendah\nBendah\u2764\ufe0fHana\nTricks\nBustah \u2764\ud83d\ude07\nEmi\u2764\ufe0fBendah",
      "profile_url": "https://www.instagram.com/mshanapaa.mrkoli/",
      "follower_count": 1993,
      "following_count": 2231,
      "post_count": 1302,
      "is_business": false,
      "is_verified": false,
      "website": "linktr.ee/MsHanapaa.MrKoli",
      "website_content": "@MsHanapaa.MrKoli Ms Hanapa\u2019a \u2764\ufe0f Mr Koli Instagram Instagram Maggie and the Mews - Hana10 Maggie and the Mews - Hana10 Ports + Paws \u2013 PORTS + PAWS - Hana15 Ports + Paws \u2013 PORTS + PAWS - Hana15 Accessories for you + your pup. Collars, leashes, harnesses, towels, customizable sweatshirts and more! Designed in Honolulu, Hawai'i' with aloha. Lulali Studio - Personalized Pet Art - HanaKoli10 Lulali Studio - Personalized Pet Art - HanaKoli10 Linktree Logo Linktree Logo Symbol and Word Mark Cookie Preferences \u2022 Report \u2022 Privacy \u2022 Explore Explore other Linktrees @ethicagm @StresstheWhiteboy @mannoloh_coorporation @zenglowretreat @noapologyband @amazedbunnyco @iamdianebell @leandra202132 @wellesmusic @amyhillismusic @TheDalihenProject @cradle.app @giacluxe @symplysymantha @tiaamilan @buildingfeasts @NewMajirel @marshatmvtravel @milkpunchmedia @thewanderingwildspa @claygroundscommunity @arshvirkktrades @amigosdedarwin @EttricksNYC @no_more_cowboys_media @michaelsilk3185 @aryee.w @coliseacausey @jessicadugandcrissien @kenyonlee @vegaanihaaste.fi @villagegaropaba @jasmne.music @Slowdownevents @billymcgourleymusic @litlebit97 @langfield.kym.l @lglcreativephotography @joyy.alegria @mindfeederz @liquifie @cretinderhamhall @Alvarobar @remathmadeeasy @ayahouse.dk View on mobile"
    },
    {
      "id": 38,
      "handle": "melissa.projectpearls",
      "display_name": "Melissa Villa",
      "bio": "Nonprofit organization\nMom to @chichai.intheair, Akua +, Keona, Mamaki and Founder & Executive Director, @projectpearls\nwww.projectpearls.org and 1 more\nmelissa.projectpearls\nFollow\nMessage",
      "profile_url": "https://www.instagram.com/melissa.projectpearls/",
      "follower_count": 1967,
      "following_count": 3321,
      "post_count": 1524,
      "is_business": false,
      "is_verified": false,
      "website": "www.projectpearls.org",
      "website_content": "About \n \n Our Vision & Mission \n Our Story \n Our Communities \n Our Team \n Our Impact Reports \n Our Partners \n \n \n Programs \n \n Education & Literacy \n Health Care & Nutrition \n Empowerment through Skills Development \n Cassie\u2019s Bag of Dreams \n BAYANIHAN (Emergency Relief Operations) \n \n \n Updates \n Press \n Partners \n \n \n \n\n \n\n VOLUNTEER \n DONATE \n\n \n \n \n \n \n \n\n \n \n\n \n \n \n\n \n \n \n \n\n \n \n \n\n \n \n \n \n \n \n\n \n\n \n\n \n\n \n\n \n\n \n\n SCHOLARSHIP PROGRAM \n\n Change a life, it will change yours too \n\n \n \n\n \n \n\n \n\n \n\n \n\n \n\n \n\n HUNGER RELIEF PROGRAM \n\n They go to bed hungry and wake up hungrier. \n \n\n \n \n\n \n\n \n\n \n\n \n\n \n\n \n\n \n\n \n\n CORPORATE SOCIAL RESPONSIBILITY \n\n Partner With Us. \n\n \n \n\n \n \n\n \n\n \n\n \n\n \n\n CELEBRATE WITH PEARLS! \n\n Share your blessings. \n\n \n \n\n \n \n\n \n\n \n\n \n\n Giving Resources & Opportunities to WoMen (G.R.O.W) \n\n CHECK OUR CATALOGUE THAT CHANGE LIVES \n\n \n \n\n \n BAYANIHAN (EMERGENCY RELIEF OPERATIONS) \n\n See our various Bayanihan initiaves \n\n \n\n \n\n \n\n \n\n \n\n \n\n \n \n\n \n \n\n \n\n A DECADE OF PROJECT PEARLS \n\n See our 10 Years of PEARLS \n \n\n \n \n \n\n \n \n \n \n\n \n \n \n \n \n\n \n \n \nDONATE\n \n \n \n \nHelp Break The Cycle\n \n \nOf Poverty, Illiteracy and Inequality. GIVE.\n \n \n \n \n \n \n \n\n \n\n \n \n \n \n \n \n \nVolunteer\n \n \n \n \nShare your time and talent.\n \n \nMake a positive impact.\n \n \n \n \n \n \n \n\n \n\n \n \n \n \n \n \n \nAdvocate\n \n \n \n \nVolunteer \n \n \nYour Voice.\n \n \n \n \n \n \n \n\n \n \n \n \n\n \n \n\n \n \n \n \n \n \n \n Project PEARLS: It's a Movement \n \n \n \n \n \n \n We are committed to extending a lifeline to the most vulnerable communities"
    },
    {
      "id": 686,
      "handle": "darkzone_ft",
      "display_name": "\u1d30\u1d2c\u1d3f\u1d37\u1dbb\u1d3c\u1d3a\u1d31",
      "bio": "Photography Videography\none moment, several takes \ud83c\udf05\ud83d\udcf8\nsurf lessons-Tours-Surfing-\n\ud83c\udf2e\ud83c\udf3f\ud83c\udfc4\u200d\u2642\ufe0f\nboard repair \ud83d\udee0\ufe0f\ud83c\udfe0\nAgenci...\u00a0\nmore\nMexico, Salina Cruz, Oaxaca\ndarkzone_ft\nFollow\nMessage\nEdit",
      "profile_url": "https://www.instagram.com/darkzone_ft/",
      "follower_count": 1966,
      "following_count": 7380,
      "post_count": 44,
      "is_business": false,
      "is_verified": false,
      "website": ""
    },
    {
      "id": 240,
      "handle": "cannie_chum_hawaiire",
      "display_name": "Cannie Chum(R) | BIC |",
      "bio": "Real Estate\nLocations LLC\nAssociate Partner,RB-22002\n\ud83c\udfc5Top 100 Hawaii Realtors \ud83c\udfc6\n\ud83c\udfe1 \u590f\u5a01\u5937\u623f\u5730\u7522\u7d93\u7d00\ud83c\udfe1\n\u2b50\ufe0f 2022 | 2023 Aloha '\u0100ina REALTOR\u00ae Awa... \nmore\nwww.locationshawaii.com/agent/cannie-chum/?aid=4138\ncannie_chum_hawaiire\nFollow\nMessage",
      "profile_url": "https://www.instagram.com/cannie_chum_hawaiire/",
      "follower_count": 1941,
      "following_count": 4768,
      "post_count": 761,
      "is_business": false,
      "is_verified": false,
      "website": "www.locationshawaii.com/agent/cannie-chum/",
      "website_content": "Menu \r\n \r\n \r\n\r\n \r\n \r\n\r\n \r\n \r\n \r\n \r\n \r\n Sign Up Free \r\n \r\n \r\n \r\n \r\n Sign Up Free \r\n \r\n \r\n \r\n \r\n \r\n \r\n \r\n \r\n \r\n \r\n \r\n Call us at 1.866.MLS.2345 or 808.377.4642 \r\n \r\n \r\n Neighborhoods \r\n MLS Search \r\n Power Search \r\n Careers \r\n \r\n Contact \r\n \r\n \r\n \r\n \r\n \u00a5 CNY \u20ac EUR \u00a5 JPY \u20a9 KRW $ USD \r\n \r\n\r\n\r\n \r\n \r\n \r\n EN CH JP KR ES \r\n \r\n\r\n \r\n \r\n \r\n \r\n \r\n\r\n \r\n \r\n \r\n \r\n Home \r\n \r\n Buy \r\n \r\n \r\n Hawaii Real Estate Power Search \r\n \r\n \r\n Oahu Real Estate \r\n Honolulu Real Estate \r\n Maui Real Estate \r\n Big Island Real Estate \r\n Kauai Real Estate \r\n MLS Search \r\n \r\n \r\n \r\n Foreclosures \r\n Open Houses \r\n New Developments \r\n \r\n Luxury Real Estate \r\n Homes Virtual Tours \r\n Homes Near Hawaii Military Bases \r\n Oahu Legal Short Term Rental Condos \r\n \r\n \r\n\r\n \r\n Power Search \r\n \r\n \r\n \r\n \r\n \r\n \r\n \r\n \r\n Hawaii's most accurate home valuation tool. \r\n \r\n Start Tracking your home's value today! \r\n \r\n \r\n \r\n \r\n \r\n Sell \r\n Agents \r\n \r\n Learn \r\n \r\n \r\n \r\n \r\n Home Buying \r\n Home Selling \r\n Investing in Real Estate \r\n Military Information \r\n Affordable Housing \r\n Oahu Legal Short Term Rental Condos \r\n \r\n \r\n Market Reports \r\n Real Estate Tools \r\n Glossary \r\n \r\n \r\n Browse All \r\n \r\n \r\n \r\n \r\n \r\n \r\n \r\n \r\n Oahu Real Estate Report \r\n \r\n Competition Continues To Set Records \r\n \r\n \r\n \r\n \r\n \r\n \r\n Seminars \r\n News \r\n Open House \r\n \r\n \r\n Careers \r\n \r\n \r\n \r\n We Are Partners In Your Success \r\n \r\n \r\n \r\n Real Estate Careers \r\n Careers In Administration \r\n \r\n \r\n Sales Support and Resources \r\n Shared Learning and Culture \r\n Grow Your Career"
    },
    {
      "id": 460,
      "handle": "rotaryeclubhi",
      "display_name": "Rotary E-Club of Hawaii",
      "bio": "The first E-Club in District 5000! Join us at our meetings, every second Monday at 12 noon HST via Zoom Meeting ID:...\u00a0\nmore\nrotaryeclubhawaii.org\nFollow\nMessage\n#beathungerhi\nService Project\nHoola Na Pua",
      "profile_url": "https://www.instagram.com/rotaryeclubhi/",
      "follower_count": 1938,
      "following_count": 3419,
      "post_count": 432,
      "is_business": false,
      "is_verified": false,
      "website": "rotaryeclubhawaii.org",
      "website_content": "e-Club of Hawaii \r\n \r\n \r\n \r\n \r\n \r\n \r\n \r\n \r\n \r\n \r\n \r\n Home \r\n \r\n \r\n \r\n\r\n \r\n \r\n Website not active \r\n \r\n The website you are trying to access is currently not active. If you are the site owner, please contact ClubRunner: \r\n 1-877-469-2582 \r\n support@clubrunner.ca \r\n \r\n \r\n \r\n\r\n\r\n\r\n \r\n \r\n \u00a9 2002\u20132026\u00a0 ClubRunner . All rights reserved.\r\n \r\n Privacy Statement \r\n\r\n | Cookie Policy \r\n | Online Help \r\n | System Requirements"
    },
    {
      "id": 60,
      "handle": "sirarrowofpersistence.sdit",
      "display_name": "Arrow the Mal",
      "bio": "\ud83c\udff9 Belgian Malinois\n\ud83c\udff9 born 12/01/24\n\ud83c\udff9 MOBILITY SD/TASK IN TRAINING\n\ud83c\udff9 TRAINED BY PERSISTENTPAWSDOGTRAINING\nFollow\nMessage",
      "profile_url": "https://www.instagram.com/sirarrowofpersistence.sdit/",
      "follower_count": 1883,
      "following_count": 1900,
      "post_count": 153,
      "is_business": false,
      "is_verified": false,
      "website": ""
    },
    {
      "id": 244,
      "handle": "laislaaloha",
      "display_name": "Samba & Lai\u0301s",
      "bio": "\ud83c\udf0e\ud83c\udf34\ud83d\udc29 Rio-Hawaii- currently on Sanibel Island - FL\nFollow\nBrasil 25\nV.O.T.A.\nHawaii #TBT\nGasparilla 24\nBrasil '23\nTampa\nAMI & Coquina\nHI 23\nWest Palm\nSiesta Key\nSt Pete\nLongboat Key\nSarasota\nSafety Harbor",
      "profile_url": "https://www.instagram.com/laislaaloha/",
      "follower_count": 1863,
      "following_count": 3995,
      "post_count": 1081,
      "is_business": false,
      "is_verified": false,
      "website": ""
    },
    {
      "id": 68,
      "handle": "tikidawg_kauai",
      "display_name": "Tiki Pet Collars Inc.",
      "bio": "Pet Supplies\nHandcrafted on the island of Kauai \ud83c\udf3a\ud83d\udccd\nCat and dog collars, harnesses, & leashes made with love \u2764\ufe0f Custom orders... \nmore\ntikidawg.com\nFollow\nMessage\nTikidawgs \ud83d\udc36\nShopNow\ud83d\ude0d\nTikikitties \ud83d\udc31\nLocations \ud83d\udccd",
      "profile_url": "https://www.instagram.com/tikidawg_kauai/",
      "follower_count": 1833,
      "following_count": 516,
      "post_count": 531,
      "is_business": false,
      "is_verified": false,
      "website": "tikidawg.com",
      "website_content": "Log in | Sign up \n \n \n \n\n \n 0 items in your cart \n \n \n\n \n\n \n \n \n \n Home \n \n \n \n \n for Tiki Dawgs Expand child menu \n \n \n \n \n Dawg Collars (buckle) \n \n \n \n \n Back Pull Harnesses \n \n \n \n \n Leashes \n \n \n \n \n Martingale (Limited Choke) Dawg Collars \n \n \n \n \n \n \n \n \n for Tiki Kittis Expand child menu \n \n \n \n \n Kitti Collars \n \n \n \n \n Kitti Harnesses \n \n \n \n \n \n \n \n \n Locations \n \n \n \n \n About \n \n \n \n \n \n\n \n Menu \n \n Account \n \n Cart \n \n \n \n\n \n \n \n\n \n \n \n \n \n \n \n \n Search \n \n \n\n \n \n\n \n \n \n Kitti Collars \n \n \n \n \n Kitti Harnesses \n \n \n \n \n Dawg Collars \n \n \n \n \n Harnesses - Dawg \n \n \n \n \n Leashes \n \n \n \n \n Martingale Collars \n \n \n \n \n Shop By Pattern \n \n \n \n \n All Products \n \n \n \n \n\n \n\n \n \n\n \n\n \n \n\n \n\n \n\n \n \n\n \n \n \n \n \n\n \n \n \n \n \n \n \n \n \n \n \n \n \n \n \n \n\n \n \n WELCOME to Tiki Pet Collars \n \n \n Aloha: Thank you for visiting our site. Discover our collection of authentic Hawaiian tropical prints handcrafted right here in the islands - on Kauai and Oahu. From vibrant hibiscus and plumeria to traditional tapa designs, our tiki-inspired collars, leashes, harnesses, and bandanas bring the spirit of aloha to your four-legged ohana member. Each piece is lovingly made in Hawaii with island-quality craftsmanship, featuring unique tropical patterns you won't find anywhere else. Whether your pup loves surfboards, sea turtles (honu), or classic Hawaiian flowers, we have the perfect island style for them. Mahalo for supporting local Hawaiian craftsmanship! Follow us on Instagram @tikidawg_kauai and Facebook"
    },
    {
      "id": 254,
      "handle": "sashasandry",
      "display_name": "Sasha Sandry",
      "bio": "\ud83c\udf3a Wahiaw\u0101, HI\n\ud83d\udccdLas Vegas, NV\nsashasandry\nFollow\nH\u2764\ufe0fme\nHa\ud83e\udd19\ud83c\udfffaii\nMrs\u2026\nL \u2764\ufe0f V E\nLions \ud83d\udc36\ud83e\udd8a\nAbhay's 40th",
      "profile_url": "https://www.instagram.com/sashasandry/",
      "follower_count": 1804,
      "following_count": 2736,
      "post_count": 369,
      "is_business": false,
      "is_verified": false,
      "website": ""
    },
    {
      "id": 100,
      "handle": "accessiblecollege",
      "display_name": "Annie | College Prep Help",
      "bio": "Helping students with physical disabilities & health conditions transition to college with ease\n\ud83e\udde0 Physical, chronic, &... \nmore\neepurl.com/goKtx1 and 1 more\nFollow\nMessage\nServices\nCourse\nPartnerships\nBTS",
      "profile_url": "https://www.instagram.com/accessiblecollege/",
      "follower_count": 1776,
      "following_count": 2611,
      "post_count": 731,
      "is_business": false,
      "is_verified": false,
      "website": "eepurl.com/goKtx1",
      "website_content": "Accessible College \n\n \n \n \n \n \n \n Sign up to receive information about upcoming events and resources from Accessible College!\u00a0\n \n * indicates required \n\n \n \n \n \n\n \n \n Name: \n \n\n Email: \n \n\n Comment: \n \n \n\n \n \n \n \n Email Address * \n \n \n \n \n \n \n \n \n \n \n \n First Name \n \n \n \n \n \n \n \n \n \n \n \n Last Name \n \n \n \n \n \n \n \n \n \n \n \n SMS Phone Number \n \n \ud83c\udda5\ud83c\udda5 \n \n \n \n \n \n \n \n \n \n Date created \n \n \n \n \n \n \n \n \n \n\n \n \n \n \n \n Categories (Choose all that apply) \n \n Parent/Family Member/Guardian: High School Student Parent/Family Member/Guardian: College Student Healthcare provider (doctor, therapist, OT/PT, etc.) School Counselor Educator Independent Educational Consultant Student Vocational Rehabilitation Non-profit Foundation University Administrator Other"
    },
    {
      "id": 281,
      "handle": "chrissiepinney",
      "display_name": "Chrissie Pinney",
      "bio": "I've lived many lives.\nCo-founder of @hanakoabrewing\nBe curious when you don't understand\nBe kind no matter what\nchrissiepinney\nFollow\nAndy\nHI timelapse\nSexism\nLove \ud83d\udc95\nBelgium\nFrance\nLondon\nIsland life\nToby",
      "profile_url": "https://www.instagram.com/chrissiepinney/",
      "follower_count": 1774,
      "following_count": 2164,
      "post_count": 1505,
      "is_business": false,
      "is_verified": false,
      "website": ""
    },
    {
      "id": 26,
      "handle": "caninepartnersoftherockies",
      "display_name": "Canine Partners of the Rockies",
      "bio": "Nonprofit organization\nCanine Partners of the Rockies places Service & Facility Dogs in CO, and provides therapeutic outreach to kids, veterans... \nmore\nPO Box 33136, Northglenn, Colorado 80223\ncpotr.org/puppy-cam and 4 more\ncaninepartnersoftherockies\nFollow\nMessage\nEvents\nOut & About\nPuppies\nTraining\nToo cute\nOur Dogs\nNews\ud83d\udcfd\ufe0f\nGraduates\nTeam Training\nTreat Us",
      "profile_url": "https://www.instagram.com/caninepartnersoftherockies/",
      "follower_count": 1751,
      "following_count": 664,
      "post_count": 1244,
      "is_business": false,
      "is_verified": false,
      "website": "cpotr.org/puppy-cam",
      "website_content": "Skip to content \n\n \n \n \n \n \n \n \n \n \n \n \n \n Aurora, Colorado | (303) 364-9040 | info@cpotr.org \n \n Facebook Instagram LinkedIn YouTube Email \n \n \n \n \n \n \n \n\n \n \n\n \n \n \n \n\n \n \n Search for: \n \n \n \n \n \n \n\n \n \n\n \n \n About Our Mission Our Team Contact Blog Shop Our Merch Our Dogs Puppy Cam Mobility Service Dogs & Facility Dogs Their Journey Community Outreach Programs Success Stories Dogs in Training Ways to Give Apply for a Dog Get Involved More Acknowledgments FAQ Resources Reports & Statements Donate About Our Mission Our Team Contact Blog Shop Our Merch Our Dogs Puppy Cam Mobility Service Dogs & Facility Dogs Their Journey Community Outreach Programs Success Stories Dogs in Training Ways to Give Apply for a Dog Get Involved More Acknowledgments FAQ Resources Reports & Statements Donate \n \n \n \n \n \n\n \n\n \n \n \n \n \n \n \n \n \n \n \n Puppy Cam January 2026 \n \n \n \n \n \n \n Puppy Cam Hailey Day 2026-02-04T16:20:34-07:00 \n \n \n Meet our newest service pups in training! \n Tune in daily from 10am\u20137pm \u00a0to watch these future service dogs learn, play, and grow in real time. \n Puppy Cam \n \n \n \n \n \n \n \n \n \n \u200b\u200bPhysical Address \n 651 Potomac Street, Suite E \nAurora, CO 80011 \n Mailing Address \n PO Box 33136 \nNorthglenn, CO 80233 \n Get In Touch \n (303) 364-9040 \n \n info@cpotr.org \n Office Hours \n Monday \u2013 Thursday \n\u200b10:00 AM \u2013 4:00 PM \n Toggle Navigation Privacy Policy Grievance Policy \u00a9 2026 Canine Partners of the Rockies, All Rights Reserved. \u2022 Website by Heyday Creative . \n \n \n \n \n Page load link"
    },
    {
      "id": 406,
      "handle": "inform_hi",
      "display_name": "InForm Design",
      "bio": "Architectural Designer\nAward Winning Architecture and Interior Design firm based in Honolulu, Hawaii.\n1357 Kapiolani Blvd, Suite 850, Honolulu, Hawaii 96814\ninform.design and 1 more\nFollow\nMessage\nAwards\nIFD Culture\nHospitality\nResidential\nEducation\nFood & Bev\nFinancial\nOffices\nLounges",
      "profile_url": "https://www.instagram.com/inform_hi/",
      "follower_count": 1740,
      "following_count": 1431,
      "post_count": 348,
      "is_business": false,
      "is_verified": false,
      "website": ""
    }
  ]
}